quara/creds/__init__.py
quara/creds/cli/__init__.py
quara/creds/cli/__main__.py
quara/creds/cli/commands/__init__.py
quara/creds/cli/commands/env.py
quara/creds/cli/commands/init.py
quara/creds/cli/commands/version.py
quara/creds/cli/subcommands/__init__.py
quara/creds/cli/subcommands/authorities/__init__.py
quara/creds/cli/subcommands/authorities/list.py
quara/creds/cli/subcommands/ca/__init__.py
quara/creds/cli/subcommands/ca/list.py
quara/creds/cli/subcommands/ca/show.py
quara/creds/cli/subcommands/ca/sign.py
quara/creds/cli/subcommands/cert/__init__.py
quara/creds/cli/subcommands/cert/list.py
quara/creds/cli/subcommands/cert/rm.py
quara/creds/cli/subcommands/cert/show.py
quara/creds/cli/subcommands/cert/sign.py
quara/creds/cli/subcommands/cert/verify.py
quara/creds/cli/subcommands/config/__init__.py
quara/creds/cli/subcommands/config/data/default.yml.j2
quara/creds/cli/subcommands/config/generate.py
quara/creds/cli/subcommands/csr/__init__.py
quara/creds/cli/subcommands/csr/import_.py
quara/creds/cli/subcommands/csr/list.py
quara/creds/cli/subcommands/csr/rm.py
quara/creds/cli/subcommands/csr/show.py
quara/creds/cli/subcommands/csr/update.py
quara/creds/cli/subcommands/key/__init__.py
quara/creds/cli/subcommands/key/gen.py
quara/creds/cli/subcommands/key/import_.py
quara/creds/cli/subcommands/key/list.py
quara/creds/cli/subcommands/key/rm.py
quara/creds/cli/subcommands/key/show.py
quara/creds/cli/utils.py
quara/creds/manager/__init__.py
quara/creds/manager/adapters/keystores/__init__.py
quara/creds/manager/adapters/keystores/azkv_keystore.py
quara/creds/manager/adapters/keystores/file_keystore.py
quara/creds/manager/adapters/storages/__init__.py
quara/creds/manager/adapters/storages/file_storage.py
quara/creds/manager/interfaces/__init__.py
quara/creds/manager/interfaces/authorities.py
quara/creds/manager/interfaces/keystore.py
quara/creds/manager/interfaces/storage.py
quara/creds/manager/manager.py
quara/creds/manager/settings.py
quara/creds/manager/user.py
quara_creds-0.10.2.dist-info/entry_points.txt
quara_creds-0.10.2.dist-info/LICENSE
quara_creds-0.10.2.dist-info/WHEEL
quara_creds-0.10.2.dist-info/METADATA
quara_creds-0.10.2.dist-info/RECORD
