Metadata-Version: 2.1
Name: quara-creds
Version: 0.10.2
Summary: 
Author: charbonnierg
Author-email: guillaume.charbonnier@araymond.com
Requires-Python: >=3.7,<4.0
Classifier: Programming Language :: Python :: 3
Classifier: Programming Language :: Python :: 3.7
Classifier: Programming Language :: Python :: 3.8
Classifier: Programming Language :: Python :: 3.9
Classifier: Programming Language :: Python :: 3.10
Classifier: Programming Language :: Python :: 3.11
Requires-Dist: Jinja2
Requires-Dist: azure-identity
Requires-Dist: azure-keyvault-secrets
Requires-Dist: cryptography
Requires-Dist: protobuf (<3.21)
Requires-Dist: rich
Requires-Dist: typer
